emacs/__init__.py
emacs/emacs.py
emacs/elisp/__init__.py
emacs/elisp/ast.py
emacs/elisp/dsl.py
emacs/elisp/exprs.py
emacs/elisp/util.py
python_emacs-0.2.1.dist-info/LICENSE
python_emacs-0.2.1.dist-info/METADATA
python_emacs-0.2.1.dist-info/WHEEL
python_emacs-0.2.1.dist-info/top_level.txt
python_emacs-0.2.1.dist-info/RECORD
