Metadata-Version: 2.1
Name: python-emacs
Version: 0.2.1
Summary: Python interface to GNU Emacs.
Home-page: https://github.com/jlumpe/python-emacs
Author: Jared Lumpe
Author-email: jared@jaredlumpe.com
Project-URL: Documentation, https://python-emacs.readthedocs.io/en/stable/
Classifier: Programming Language :: Python :: 3
Classifier: Programming Language :: Python :: 3.6
Classifier: Programming Language :: Python :: 3.7
Classifier: Programming Language :: Python :: 3.8
Classifier: Programming Language :: Python :: 3.9
Classifier: Programming Language :: Python :: 3.10
Classifier: Programming Language :: Python :: 3.11
Classifier: Programming Language :: Python :: 3.12
Classifier: Programming Language :: Emacs-Lisp
Classifier: License :: OSI Approved :: MIT License
Classifier: Development Status :: 4 - Beta
Classifier: Topic :: Text Editors :: Emacs
Requires-Python: >=3.6
License-File: LICENSE
